norma2/__dependencies__.py
norma2/__init__.py
norma2/__main__.py
norma2/__version__.py
norma2/checkers/c/check_c.py
norma2/checkers/c/comma.py
norma2/checkers/c/comment.py
norma2/checkers/c/header.py
norma2/checkers/c/indent.py
norma2/checkers/c/libc_func.py
norma2/checkers/c/nb_function_per_file.py
norma2/checkers/c/nb_line_per_func.py
norma2/checkers/c/nb_params.py
norma2/checkers/c/nested_branch.py
norma2/checkers/c/operator.py
norma2/checkers/c/parenthesis.py
norma2/checkers/c/preprocessor.py
norma2/checkers/c/snake_case.py
norma2/checkers/c/statements.py
norma2/checkers/c/subscriptor.py
norma2/checkers/c/tabulation.py
norma2/checkers/c/two_space.py
norma2/checkers/check.py
norma2/checkers/default/check_default.py
norma2/checkers/for_all/check_for_all.py
norma2/checkers/for_all/columns.py
norma2/checkers/for_all/extension.py
norma2/checkers/for_all/leading_line.py
norma2/checkers/for_all/trailing_line.py
norma2/checkers/for_all/trailing_space.py
norma2/checkers/haskell/check_haskell.py
norma2/checkers/haskell/header.py
norma2/checkers/makefile/check_makefile.py
norma2/config/config.py
norma2/config/config_class.py
norma2/config/from_cmdline.py
norma2/config/from_gitignore.py
norma2/config/from_json.py
norma2/errors/__init__.py
norma2/errors/norm.py
norma2/main.py
norma2/parser/_file.py
norma2/parser/cfile.py
norma2/parser/file.py
norma2/parser/get_files.py
norma2/parser/hsfile.py
norma2/parser/makefile.py
norma2/regexs/r_comment.py
norma2/regexs/r_declaration.py
norma2/regexs/r_empty.py
norma2/regexs/r_for.py
norma2/regexs/r_function.py
norma2/regexs/r_if.py
norma2/regexs/r_imperativ.py
norma2/regexs/r_macro.py
norma2/regexs/r_prototype.py
norma2/regexs/r_struct.py
norma2/regexs/r_text.py
norma2/regexs/r_union.py
norma2/regexs/r_while.py
norma2/regexs/regexs_class.py
norma2/show_stats.py
norma2/tests/__init__.py
norma2/tests/truecode/bad_code/Makefile
norma2/tests/truecode/bad_code/a.out
norma2/tests/truecode/bad_code/chempa/sample1.c
norma2-0.0.2.dist-info/entry_points.txt
norma2-0.0.2.dist-info/WHEEL
norma2-0.0.2.dist-info/METADATA
norma2-0.0.2.dist-info/RECORD
