Metadata-Version: 2.1
Name: norma2
Version: 0.0.2
Summary: check c epitech coding style
License: MIT
Author-email: Xavier Mitault <xavier.mitault@epitech.eu>
Requires-Python: >=3.10
Classifier: Environment :: Console
Classifier: License :: OSI Approved :: MIT License
Classifier: Operating System :: OS Independent
Classifier: Programming Language :: C
Classifier: Programming Language :: Python :: 3
Classifier: Topic :: Software Development :: Quality Assurance
Requires-Dist: igittigitt>=2.1.2
Requires-Dist: markdown>=3.4.1
Requires-Dist: regex>=2022.9.13
Requires-Dist: rich-argparse>=0.3.1
Requires-Dist: rich>=12.6.0
Requires-Dist: shtab>=1.5.7
